LICENSE
MANIFEST.in
README.rst
setup.py
djangorestframework_signed_permissions.egg-info/PKG-INFO
djangorestframework_signed_permissions.egg-info/SOURCES.txt
djangorestframework_signed_permissions.egg-info/dependency_links.txt
djangorestframework_signed_permissions.egg-info/requires.txt
djangorestframework_signed_permissions.egg-info/top_level.txt
docs/Makefile
docs/conf.py
docs/index.rst
docs/make.bat
docs/usage.rst
signedpermissions/__init__.py
signedpermissions/permissions.py
signedpermissions/signing.py
signedpermissions/views.py
tests/__init__.py
tests/models.py
tests/settings.py
tests/urls.py
tests/views.py
tests/tests/__init__.py
tests/tests/test_permissions.py