Metadata-Version: 1.1
Name: djangorestframework-signed-permissions
Version: 0.0.5
Summary: Allow access to your REST resources via a signed url
Home-page: https://github.com/chewse/djangorestframework-signed-permissions
Author: Chewse
Author-email: james@chewse.com
License: MIT License
Platform: UNKNOWN
Classifier: Environment :: Web Environment
Classifier: Framework :: Django
Classifier: Intended Audience :: Developers
Classifier: Operating System :: OS Independent
Classifier: Programming Language :: Python
Classifier: Programming Language :: Python :: 2
Classifier: Programming Language :: Python :: 3
